genie_partner_sdk/__init__.py
genie_partner_sdk/auth.py
genie_partner_sdk/client.py
genie_partner_sdk/model.py
genie_partner_sdk/py.typed
genie_partner_sdk-1.0.11.dist-info/METADATA
genie_partner_sdk-1.0.11.dist-info/WHEEL
genie_partner_sdk-1.0.11.dist-info/licenses/LICENSE
genie_partner_sdk-1.0.11.dist-info/RECORD
