Metadata-Version: 2.4
Name: genie_partner_sdk
Version: 1.0.11
Summary: An SDK to interact with the AladdinConnect (or OHD) partner API
Project-URL: Homepage, https://github.com/genie-garage/aladdin-python-sdk
Project-URL: Issues, https://github.com/genie-garage/aladdin-python-sdk/issues
Author-email: Adam Johnston <adam_johnston@geniecompany.com>
License: Copyright (c) 2025 The Genie Company
License-File: LICENSE
Classifier: Operating System :: OS Independent
Classifier: Programming Language :: Python :: 3
Requires-Python: >=3.11
